myfy/data/__init__.py
myfy/data/config.py
myfy/data/errors.py
myfy/data/extensions.py
myfy/data/migrations.py
myfy/data/module.py
myfy/data/session.py
myfy/data/testing.py
myfy/data/version.py
myfy_data-0.1.2a83.dist-info/METADATA
myfy_data-0.1.2a83.dist-info/WHEEL
myfy_data-0.1.2a83.dist-info/entry_points.txt
myfy_data-0.1.2a83.dist-info/RECORD
