Metadata-Version: 2.4
Name: myfy-data
Version: 0.1.2a83
Summary: Database/ORM module for myfy framework
Requires-Python: >=3.12
Requires-Dist: aiosqlite>=0.20.0
Requires-Dist: alembic>=1.13.0
Requires-Dist: myfy-core==0.1.2a83
Requires-Dist: sqlalchemy[asyncio]>=2.0
